str_message/VERSION
str_message/__init__.py
str_message/_message.py
str_message/extra/__init__.py
str_message/extra/func_defs.py
str_message/extra/mcps.py
str_message/patches/__init__.py
str_message/patches/patch_openai.py
str_message/types/__init__.py
str_message/types/chat_completion_messages.py
str_message/types/func_def.py
str_message/utils/__init__.py
str_message/utils/content_parts_from_str.py
str_message/utils/ensure_tz.py
str_message/utils/message_from_any.py
str_message/utils/message_from_chat_cmpl.py
str_message/utils/message_from_chat_cmpl_input_message.py
str_message/utils/message_from_chat_cmpl_message.py
str_message/utils/message_from_response_input_item.py
str_message/utils/message_from_response_output_item.py
str_message/utils/messages_to_chat_cmpl_input_messages.py
str_message/utils/messages_to_harmony.py
str_message/utils/messages_to_response_input_param.py
str_message/utils/messages_to_sharegpt.py
str_message/utils/might_reasoning.py
str_message/utils/might_temperature.py
str_message/utils/response_input_content_to_str.py
str_message/utils/safe_pop.py
str_message-0.8.0.dist-info/METADATA
str_message-0.8.0.dist-info/WHEEL
str_message-0.8.0.dist-info/licenses/LICENSE
str_message-0.8.0.dist-info/RECORD
