Metadata-Version: 2.4
Name: str-message
Version: 0.8.0
Summary: Any Message Could be a String, for LLM Usage
License: MIT
License-File: LICENSE
Author: Allen Chou
Author-email: f1470891079@gmail.com
Requires-Python: >=3.11,<4
Classifier: License :: OSI Approved :: MIT License
Classifier: Programming Language :: Python :: 3
Classifier: Programming Language :: Python :: 3.11
Classifier: Programming Language :: Python :: 3.12
Classifier: Programming Language :: Python :: 3.13
Classifier: Programming Language :: Python :: 3.14
Requires-Dist: cachetools
Requires-Dist: dictpress (>=0.3.0)
Requires-Dist: durl-py (>=0.1.1)
Requires-Dist: json-repair
Requires-Dist: openai
Requires-Dist: openai-agents
Requires-Dist: openai-harmony
Requires-Dist: openai-usage
Requires-Dist: pydantic (>=2)
Requires-Dist: str-or-none
Requires-Dist: tiktoken
Requires-Dist: uuid-utils
Project-URL: Homepage, https://github.com/allen2c/str-message
Project-URL: PyPI, https://pypi.org/project/str-message/
Project-URL: Repository, https://github.com/allen2c/str-message
